Metadata-Version: 2.4
Name: mcp-ollama-fastmcp
Version: 0.1.4
Summary: MCP server for Ollama integration
Project-URL: Homepage, https://github.com/fastmcp-me/mcp-ollama#readme
Project-URL: Repository, https://github.com/fastmcp-me/mcp-ollama.git
Project-URL: Issues, https://github.com/fastmcp-me/mcp-ollama/issues
Author-email: Matt Green <emgeee@users.noreply.github.com>
License: MIT
License-File: LICENSE
Keywords: anthropic,claude,llm,mcp,ollama
Classifier: Development Status :: 4 - Beta
Classifier: Intended Audience :: Developers
Classifier: License :: OSI Approved :: MIT License
Classifier: Programming Language :: Python :: 3
Classifier: Programming Language :: Python :: 3.10
Classifier: Programming Language :: Python :: 3.11
Classifier: Programming Language :: Python :: 3.12
Requires-Python: >=3.10
Requires-Dist: mcp[cli]
Requires-Dist: ollama
Provides-Extra: dev
Requires-Dist: hatch; extra == 'dev'
Requires-Dist: ruff; extra == 'dev'
